ecusolver/__init__.py
ecusolver/lineales.py
ecusolver/no_lineales.py
ecuacionsolver-0.1.0.dist-info/METADATA
ecuacionsolver-0.1.0.dist-info/WHEEL
ecuacionsolver-0.1.0.dist-info/top_level.txt
ecuacionsolver-0.1.0.dist-info/RECORD
