Metadata-Version: 2.4
Name: ecuacionsolver
Version: 0.1.0
Summary: Librería en Python para resolver sistemas de ecuaciones lineales y no lineales
Home-page: https://github.com/usuario/ecusolver
Author: Alexis Orantes
Author-email: os23002@gmail.com
Classifier: Development Status :: 5 - Production/Stable
Classifier: Intended Audience :: Education
Classifier: License :: OSI Approved :: MIT License
Classifier: Programming Language :: Python :: 3
Classifier: Topic :: Education
Requires-Python: >=3.6
Requires-Dist: numpy
Dynamic: author
Dynamic: author-email
Dynamic: classifier
Dynamic: description
Dynamic: description-content-type
Dynamic: home-page
Dynamic: requires-dist
Dynamic: requires-python
Dynamic: summary
